AUTHORS.rst
CONTRIBUTING.rst
LICENSE
MANIFEST.in
README.rst
setup.cfg
setup.py
docs/Makefile
docs/authors.rst
docs/conf.py
docs/contributing.rst
docs/history.rst
docs/index.rst
docs/installation.rst
docs/make.bat
docs/readme.rst
docs/usage.rst
erroremail/__init__.py
erroremail.egg-info/PKG-INFO
erroremail.egg-info/SOURCES.txt
erroremail.egg-info/dependency_links.txt
erroremail.egg-info/not-zip-safe
erroremail.egg-info/top_level.txt
tests/__init__.py
tests/test_send_email.py